{"type":"champion","format":"standAloneComplex","version":"4.15.1","data":{"Rengar":{"id":"Rengar","key":"107","name":"렝가","title":"추적하는 사자","image":{"full":"Rengar.png","sprite":"champion2.png","group":"champion","x":96,"y":48,"w":48,"h":48},"skins":[{"id":"107000","num":0,"name":"default"},{"id":"107001","num":1,"name":"괴물사냥꾼 렝가"},{"id":"107002","num":2,"name":"암흑 사냥꾼 렝가"}],"lore":"상상해보라. 벽마다 빼곡하게 걸려 있는 두개골과 뿔, 발톱, 송곳니... 단순히 사슴이나 멧돼지의 것이 아니라 발로란에서 가장 강하고 난폭하다는 야수들의 흔적이다. 전리품 수집가인 렝가의 은신처는 이렇게 지금까지 모아 온 자랑스러운 수집품으로 가득하다. 그러나 렝가는 더 강하고 더 무서운 짐승들을 사냥하기 위해 오늘도 추적을 계속하고 있다. 한 번도 사냥에 실패한 적이 없을 것 같아 보이는 그지만, 사실은 딱 한 번 유일하게 쓰러뜨리지 못한 사냥감도 존재한다. 렝가는 그 강력한 괴물과 다시 맞닥뜨릴 바로 그 날을 대비하고 있는 것이다. 사냥감을 해치울 때마다 늘 충분히 시간을 들여 싸움의 과정을 기억에 새기고, 희생물들의 신체적 특징을 하나하나 분석해보곤 하는 것도 이런 연유다.<br><br>렝가는 사냥꾼의 혼을 지닌 채 태어났다. 그는 아직 갓 난 사자 새끼일 때 무리에서 독립한 이상한 짐승이었다. 자신이 학살한 사냥감들의 두개골을 쌓아 경계를 확실히 표시한 그는 자신만의 영토를 소유하고, 홀로 지배하겠노라고 선언했다. 그렇게 하면 욕망을 조금이나마 제어할 수 있을 거라고 생각한 것이다. 그러나 렝가에겐 이 땅의 절대적인 군주가 된다는 것조차 사냥의 갈증을 풀어줄 수는 없었다. 그 어떤 야수도 이미 그의 도전 의식을 충족시켜주지 못했고 렝가는 격에 맞는 상대를 찾지 못한 채 사냥꾼으로서의 면모를 점차 잃어가고 있었다. 더 이상 무엇을 경험해도 가슴이 떨리지 않을 때 우리가 절망하는 것처럼. 렝가에게 있어 사냥의 전율을 더 이상 느낄 수 없을지도 모른다는 공포는 그에게 깊은 절망감을 선사하기에 충분했다. 그러나 역시 세상은 넓고, 그 어떤 절망에도 끝이 있는 법. 렝가는 그 '괴물'과 마주쳤다.<br><br>놈의 습성은 충격 그 자체였으며, 이 생경한 괴물의 외형은 세상의 그 어떤 생명체와도 달라 보였다. 괴물은 거대한 낫 같은 발톱을 휘두르며 자기 앞에 발을 잘못 들인 동물들을 죄다 먹어치웠다. 도전할만한 상대를 맞닥뜨렸다는 기쁨에 도취된 렝가는 성급하게 매복 공격을 시도했다. 그러나 이 괴물은 이전에 만났던 사냥감들과 차원이 달랐다. 둘은 처절한 전투 끝에 치유할 수 없는 심각한 부상을 입었고, 이날 한쪽 눈을 잃어버린 렝가는 자존심에도 큰 상처를 입었다. 내가 후퇴를 하다니... 목숨도 끊어놓지 못하고, 오히려 한심하게 상처나 입고! 그렇게 며칠 동안이나 렝가는 삶과 죽음의 문턱을 넘나들었다. 몸은 극심한 고통에 시달렸는데, 정작 마음 깊은 곳에서는 희미한 기쁨이 차오르기 시작했다. 이 세상에 제대로 된 사냥감이 아직도 남아 있다니! 렝가는 마음을 급하게 먹지 않았다. 괴물을 처치하는 기쁨을 좀 더 오래 아껴두고 싶었던 것이다. 그리하여 그는 은신처 안 가장 넓은 벽에 자리를 비워두고, 지금껏 모아 온 전리품들의 한복판에 놈의 두개골을 걸게 될 날을 손꼽아 기다리고 있다.<br><br>''약한 자를 먹이로 삼는 건 생존을 위한 일이지. 하지만 강한 놈을 먹이로 삼을 땐 삶의 희열을 누릴 수 있다.''<br>-- 렝가","blurb":"상상해보라. 벽마다 빼곡하게 걸려 있는 두개골과 뿔, 발톱, 송곳니... 단순히 사슴이나 멧돼지의 것이 아니라 발로란에서 가장 강하고 난폭하다는 야수들의 흔적이다. 전리품 수집가인 렝가의 은신처는 이렇게 지금까지 모아 온 자랑스러운 수집품으로 가득하다. 그러나 렝가는 더 강하고 더 무서운 짐승들을 사냥하기 위해 오늘도 추적을 계속하고 있다. 한 번도 사냥에 실패한 적이 없을 것 같아 보이는 그지만, 사실은 딱 한 번 유일하게 쓰러뜨리지 못한 ...","allytips":["- 렝가의 궁극기는 팀간 전투나 소규모 교전에서 1순위 제거 대상을 찾아내 암살하는 데 사용하세요.","- 렝가의 효율은 강화된 스킬을 상황에 맞춰 사용하는 데에서 결정됩니다. 잘 선택해 강화하세요!","- 적을 추적할 때는 반드시 수풀을 통과하여, 기본 지속 효과를 최대한 활용하세요."],"enemytips":["- 렝가는 야성 게이지가 가득 차면 강화된 스킬을 사용하므로, 야성 게이지가 낮을 때 맞서 싸우세요.","- 기본 지속 효과로 인해 렝가는 수풀 속에서 도약 공격을 할 수 있습니다. 수풀 근처에서는 가능한 한 교전을 피하는 것이 좋습니다.","- 렝가는 궁극기로 일시적인 은신 상태에 들어갈 수 있으니, 부상을 입었을 땐 혼자 다니지 않도록 하세요."],"tags":["Assassin","Fighter"],"partype":"Ferocity","info":{"attack":7,"defense":4,"magic":2,"difficulty":8},"stats":{"hp":435.0,"hpperlevel":90.0,"mp":5.0,"mpperlevel":0.0,"movespeed":345.0,"armor":20.0,"armorperlevel":3.5,"spellblock":30.0,"spellblockperlevel":1.25,"attackrange":125.0,"hpregen":3.6,"hpregenperlevel":0.4,"mpregen":0.0,"mpregenperlevel":0.0,"crit":0.0,"critperlevel":0.0,"attackdamage":55.0,"attackdamageperlevel":3.0,"attackspeedoffset":-0.08,"attackspeedperlevel":2.85},"spells":[{"id":"RengarQ","name":"포악함","description":"렝가의 다음 기본 공격이 추가 피해를 입힙니다.<br>야성 효과: 렝가의 피해량이 증가하며, 공격 속도와 공격력이 상승합니다.","tooltip":"3초 이내에 이루어지는 다음번 기본 공격은 렝가의 공격력의 {{ e4 }}% <span class=\"colorF88017\">({{ f3 }})</span> + {{ e1 }}의 물리 피해를 입힙니다.<br><br><span class=\"colorEDDA74\">야성 효과:</span> 3초 이내에 이루어지는 다음번 기본 공격은 렝가의 공격력의 150% <span class=\"colorFF8C00\">{{ f1 }}</span> + {{ f2 }}의 물리 피해를 입히고 {{ e3 }}초 동안 공격 속도가 {{ f4 }}% 공격력이 {{ e6 }}% 증가합니다. (피해량과 공격 속도는 렝가의 레벨에 비례)</span>","leveltip":{"label":["공격 %","추가 피해량","재사용 대기시간"],"effect":["{{ e4 }}% -> {{ e4NL }}%","{{ e1 }} -> {{ e1NL }}","{{ ammorechargetime }}->{{ ammorechargetimenNL }}"]},"maxrank":5,"cooldown":[0.5,0.5,0.5,0.5,0.5],"cooldownBurn":"0.5","cost":[0,0,0,0,0],"costBurn":"0","effect":[null,[30,60,90,120,150],[150,150,150,150,150],[5,5,5,5,5],[100,105,110,115,120],[100,100,100,100,100],[10,10,10,10,10]],"effectBurn":[null,"30/60/90/120/150","150","5","100/105/110/115/120","100","10"],"vars":[{"link":"@dynamic.attackdamage","coeff":1.0,"key":"f1","dyn":"+"}],"costType":"Builds1Ferocity","range":"self","rangeBurn":"self","image":{"full":"RengarQ.png","sprite":"spell7.png","group":"spell","x":240,"y":96,"w":48,"h":48},"resource":"야성 1회 중첩"},{"id":"RengarW","name":"전투의 포효","description":"렝가가 전투의 포효를 내질러 적들에게 피해를 입히며, 짧은 시간 동안 방어력과 마법 저항력이 증가합니다.<br>야성 효과: 렝가가 체력을 큰 폭으로 회복합니다.","tooltip":"범위 내의 적들에게 {{ e5 }} <span class=\"color99FF99\">(+{{ a1 }})</span>의 마법 피해를 입힙니다. 렝가의 방어력과 마법 저항력이 {{ e6 }}초 동안 {{ e3 }}만큼 오릅니다. 챔피언이나 대형 몬스터를 맞힐 때마다 추가 방어력과 마법 저항력이 {{ e7 }}% 오릅니다.<br><br><span class=\"colorEDDA74\">야성 효과: </span>범위 내의 적들에게 {{ f2 }} <span class=\"color99FF99\">(+{{ a1 }})</span>의 마법 피해를 입히고, 일반 스킬 공격에 대한 방어력이 증가하며, 잃은 체력에 비례하여 {{ f1 }}에서 {{ f3 }}의 체력이 회복됩니다. (체력 회복 및 피해량은 렝가의 레벨에 비례)","leveltip":{"label":["피해량","방어력과 마법 저항력"],"effect":["{{ e5 }} -> {{ e5NL }}","{{ e3 }} -> {{ e3NL }}"]},"maxrank":5,"cooldown":[0.5,0.5,0.5,0.5,0.5],"cooldownBurn":"0.5","cost":[0,0,0,0,0],"costBurn":"0","effect":[null,[25,30,35,40,45],[10,15,20,25,30],[10,15,20,25,30],[100,150,200,250,300],[50,80,110,140,170],[4,4,4,4,4],[50,50,50,50,50]],"effectBurn":[null,"25/30/35/40/45","10/15/20/25/30","10/15/20/25/30","100/150/200/250/300","50/80/110/140/170","4","50"],"vars":[{"link":"spelldamage","coeff":0.8,"key":"a1"}],"costType":"Builds1Ferocity","range":[500,500,500,500,500],"rangeBurn":"500","image":{"full":"RengarW.png","sprite":"spell7.png","group":"spell","x":288,"y":96,"w":48,"h":48},"resource":"야성 1회 중첩"},{"id":"RengarE","name":"올가미 투척","description":"렝가가 올가미를 투척하여, 처음 맞은 대상에게 짧은 시간 동안 둔화를 겁니다.<br>야성 효과: 대상을 제자리에 묶습니다.","tooltip":"올가미를 던져 {{ e1 }}<span class=\"colorF88017\"> (+{{ a1 }})</span>의 물리 피해를 입히고, 2.5초 동안 적을 {{ e3 }}% 느리게 만듭니다. 둔화 효과는 시간이 흐를수록 감소합니다.<br><br><span class=\"colorEDDA74\">야성 효과:</span> {{ f1 }}<span class=\"colorF88017\"> (+{{ a1 }})</span>의 물리 피해를 입히고, 일반적인 둔화에 더하여 {{ e5 }}초 동안 대상을 제자리에 묶습니다. (피해량은 렝가의 레벨에 비례)","leveltip":{"label":["피해량","둔화 비율"],"effect":["{{ e1 }} -> {{ e1NL }}","{{ e3 }}% -> {{ e3NL }}%"]},"maxrank":5,"cooldown":[0.5,0.5,0.5,0.5,0.5],"cooldownBurn":"0.5","cost":[0,0,0,0,0],"costBurn":"0","effect":[null,[50,100,150,200,250],[20,20,20,20,20],[60,65,70,75,80],[2.5,2.5,2.5,2.5,2.5],[1.75,1.75,1.75,1.75,1.75]],"effectBurn":[null,"50/100/150/200/250","20","60/65/70/75/80","2.5","1.75"],"vars":[{"link":"bonusattackdamage","coeff":0.7,"key":"a1"}],"costType":"Builds1Ferocity","range":[1000,1000,1000,1000,1000],"rangeBurn":"1000","image":{"full":"RengarE.png","sprite":"spell7.png","group":"spell","x":336,"y":96,"w":48,"h":48},"resource":"야성 1회 중첩"},{"id":"RengarR","name":"사냥의 전율","description":"렝가가 맹수의 본능을 발동해 은신 상태가 되며, 주위 넓은 반경 안에 있는 모든 적 챔피언을 드러냅니다. 은신 상태에서는 적에게 갈 때 이동 속도가 상승하고, 다음 공격 시 도약하게 됩니다. 또한, 이동 속도가 빨라지며 은신이 풀린 후에는 야성이 빠르게 중첩됩니다.","tooltip":"렝가가 1초 후에(피해를 입을 경우 3초 후) {{ e5 }}초 동안 은신 상태가 되며 사거리 {{ e3 }} 내에 있는 적 챔피언들을 드러냅니다. 은신 상태에서 렝가는 적 챔피언에게 향해 갈 때 이동 속도가 {{ e4 }}% 상승하고, 다음번 공격 시 도약합니다.<br><br>은신이 풀리면 렝가의 이동 속도가 {{ e1 }}% 상승하며 {{ e7 }}초에 걸쳐 야성이 5 중첩됩니다.","leveltip":{"label":["이동 속도","재사용 대기시간","감지 범위"],"effect":[" {{ e1 }}% -> {{ e1NL }}%","{{ cooldown }} -> {{ cooldownnNL }}","{{ e3 }} -> {{ e3NL }}"]},"maxrank":3,"cooldown":[150,110,70],"cooldownBurn":"150/110/70","cost":[0,0,0],"costBurn":"0","effect":[null,[25,35,45],[5,5,5],[2000,3000,4000],[15,15,15],[7,7,7],[3,3,3],[5,5,5]],"effectBurn":[null,"25/35/45","5","2000/3000/4000","15","7","3","5"],"vars":[],"costType":"Builds5Ferocity","range":[2000,3000,4000],"rangeBurn":"2000/3000/4000","image":{"full":"RengarR.png","sprite":"spell7.png","group":"spell","x":384,"y":96,"w":48,"h":48},"resource":"야성 5회 중첩"}],"passive":{"name":"보이지 않는 포식자","description":"렝가는 수풀 속에서나 은신 상태에서는 기본 공격 시 적에게 도약합니다.<br><br><span class=\"colorEDDA74\">적에게 스킬 공격을 가하면 야성이 1씩 중첩됩니다. 야성이 5번 중첩되면 렝가의 다음 스킬이 강화되고, 추가 효과가 부여됩니다.</span>","image":{"full":"Rengar_Passive.png","sprite":"passive2.png","group":"passive","x":96,"y":48,"w":48,"h":48}},"recommended":[{"champion":"Rengar","title":"Map12","type":"riot","map":"12","mode":"ARAM","priority":false,"blocks":[{"type":"starting","recMath":false,"items":[{"id":"1001","count":1},{"id":"1054","count":1},{"id":"1055","count":1},{"id":"2003","count":2}]},{"type":"essential","recMath":false,"items":[{"id":"3111","count":1},{"id":"3078","count":1}]},{"type":"offensive","recMath":false,"items":[{"id":"3181","count":1},{"id":"3184","count":1},{"id":"3153","count":1}]},{"type":"defensive","recMath":false,"items":[{"id":"3065","count":1},{"id":"3022","count":1},{"id":"3143","count":1}]},{"type":"consumables","recMath":false,"items":[{"id":"2003","count":1}]}]},{"champion":"Rengar","title":"RengarDM","type":"riot","map":"8","mode":"ASCENSION","priority":false,"blocks":[{"type":"starting","recMath":false,"items":[{"id":"1001","count":1},{"id":"1062","count":1},{"id":"2003","count":2}]},{"type":"essential","recMath":false,"items":[{"id":"3111","count":1},{"id":"3044","count":1},{"id":"3068","count":1}]},{"type":"offensive","recMath":false,"items":[{"id":"3078","count":1},{"id":"3071","count":1},{"id":"3153","count":1}]},{"type":"defensive","recMath":false,"items":[{"id":"3065","count":1},{"id":"3143","count":1}]},{"type":"consumables","recMath":false,"items":[{"id":"2003","count":1}]}]},{"champion":"Rengar","title":"RengarDM","type":"riot","map":"8","mode":"ODIN","priority":false,"blocks":[{"type":"starting","recMath":false,"items":[{"id":"1001","count":1},{"id":"1062","count":1},{"id":"2003","count":2}]},{"type":"essential","recMath":false,"items":[{"id":"3111","count":1},{"id":"3044","count":1},{"id":"3068","count":1}]},{"type":"offensive","recMath":false,"items":[{"id":"3078","count":1},{"id":"3071","count":1},{"id":"3153","count":1}]},{"type":"defensive","recMath":false,"items":[{"id":"3065","count":1},{"id":"3143","count":1}]},{"type":"consumables","recMath":false,"items":[{"id":"2003","count":1}]}]},{"champion":"Rengar","title":"RengarFB","type":"riot","map":"12","mode":"FIRSTBLOOD","priority":false,"blocks":[{"type":"starting","items":[{"id":"1075","count":1},{"id":"2003","count":1},{"id":"3342","count":1}]},{"type":"essential","items":[{"id":"3111","count":1},{"id":"1053","count":1},{"id":"3044","count":1}]},{"type":"offensive","items":[{"id":"3166","count":1},{"id":"3074","count":1},{"id":"3078","count":1}]},{"type":"defensive","items":[{"id":"3065","count":1},{"id":"3026","count":1},{"id":"3022","count":1}]},{"type":"Consumables","items":[{"id":"2003","count":1},{"id":"2044","count":1}]}]},{"champion":"Rengar","title":"RengarTT","type":"riot","map":"10","mode":"CLASSIC","priority":false,"blocks":[{"type":"starting","recMath":false,"items":[{"id":"1001","count":1},{"id":"1055","count":1},{"id":"2003","count":1},{"id":"3417","count":1}]},{"type":"essential","recMath":false,"items":[{"id":"3111","count":1},{"id":"3159","count":1},{"id":"3078","count":1}]},{"type":"offensive","recMath":false,"items":[{"id":"3071","count":1},{"id":"3153","count":1},{"id":"3074","count":1}]},{"type":"defensive","recMath":false,"items":[{"id":"3068","count":1},{"id":"3143","count":1},{"id":"3065","count":1}]},{"type":"consumables","recMath":false,"items":[{"id":"2003","count":1}]}]}]}}}