{"type":"champion","format":"standAloneComplex","version":"4.12.2","data":{"Lucian":{"id":"Lucian","key":"236","name":"路西恩","title":"驅魔聖槍","image":{"full":"Lucian.png","sprite":"champion1.png","group":"champion","x":384,"y":48,"w":48,"h":48},"skins":[{"id":"236000","num":0,"name":"default"},{"id":"236001","num":1,"name":"戰鬥傭兵 路西恩"},{"id":"236002","num":2,"name":"足球先生 路西恩"}],"lore":"路西恩使用的武器是一個充滿古老力量的遺跡，他堅定地挺身而出，對抗不死族。他冷酷的信念從未動搖過，以強大的淨化之火驅逐所有狂暴的恐怖力量。路西恩孑然一身地執行著一項任務：淨化所有被禁錮的不死亡魂，為了他身在其中的永恆摯愛…。<br><br>路西恩與席安娜是天造地設的一對，從兩人手中各自擁有卻又彷若雙生的武器可見一斑。年復一年，他們不斷對抗符文大地上的黑暗，讓那些被黯影啃噬的靈魂重獲光明；他們的名字就代表了正義。絕不退縮的犧牲奉獻與溫暖人心的仁慈善良，是這對愛侶最深植人心的形象。路西恩與席安娜可謂兩人同心、密不可分。<br><br>雖然路西恩和席安娜不停地四處奔波，也克服了能擊潰多數戰士的恐懼，但這些都遠不及他們在闇影島所見的景象…當島上的邪惡生物傾巢而出，在符文大地上蠢蠢欲動時，他們倆就彼此約定要消滅所有的惡靈，追殺到天涯海角也在所不惜。這是個相當艱辛的任務，但在這對無所畏懼的雙人搭檔眼中根本算不上阻礙，直到他們遇上了喪心病狂的死神 ─ 瑟雷西。路西恩與席安娜已算是相當見多識廣，但面對瑟雷西這樣如此狡詐殘酷的生物卻是頭一遭。雙方展開了激戰，而瑟雷西使出了一個陰險無比的伎倆，在路西恩眼前上演了他內心最不願見到的畫面：席安娜的靈魂被攫取了，並且被永遠困在魂魄的監牢中。路西恩頓失了他的愛人，一個他再也無法挽回的伴侶…有生以來，他首次感到孤獨，而殲滅不死族的任務也從此必須獨自面對。<br><br>鍊魂獄長在那場惡鬥中帶走了席安娜，對路西恩來說就形同撕裂了他的靈魂，但闇影島最可怕的敵人也就此誕生了 ─ 路西恩下定鋼鐵般的決心，他將獵殺淨化所有符文大地上的黑暗生物，至死方休。為了與席安娜的榮耀記憶相伴，路西恩拾起了她遺落的武器，誓言他會完成使命，並實現兩人的約定。兀自揮舞手上的雙槍對抗著被黑暗腐蝕的靈魂，路西恩明白，即使已經失去了席安娜的靈魂，但淨化符文大地的希望不會消逝，而這將能使她的愛人獲得安息。<br><br>「心存感激吧。我將賜予死亡的恩典，饒恕你免受永恆的折磨。」─ 路西恩","blurb":"路西恩使用的武器是一個充滿古老力量的遺跡，他堅定地挺身而出，對抗不死族。他冷酷的信念從未動搖過，以強大的淨化之火驅逐所有狂暴的恐怖力量。路西恩孑然一身地執行著一項任務：淨化所有被禁錮的不死亡魂，為了他身在其中的永恆摯愛…。<br><br>路西恩與席安娜是天造地設的一對，從兩人手中各自擁有卻又彷若雙生的武器可見一斑。年復一年，他們不斷對抗符文大地上的黑暗，讓那些被黯影啃噬的靈魂重獲光明；他們的名字就代表了正義。絕不退縮的犧牲奉獻與溫暖人心的仁慈善良，是這對愛侶最深植人心的形象。...","allytips":["- 理想的爆發攻擊是以冷酷進擊和鋒芒貫穿造成連續技。","- 烈炎鐵血會形成星星的爆炸圖形。試著將星星圖形串聯起來攻擊敵方英雄。","- 一旦選擇了赤色屠戮的角度之後，就無法更改了，好好尋找最佳角度吧！","- 因為被動技能光之獵手的關係，路西恩在物理攻擊上佔的優勢比攻速更多。"],"enemytips":["- 路西恩有強大的爆發力，但是持續傷害不足。","- 路西恩無法改變赤色屠戮的方向，利用這個優勢來躲避子彈。","- 鋒芒貫穿並不會讓路西恩獲得額外的攻擊範圍。當發動技能時他還是需要攻擊在範圍內的目標。 猜測路西恩可能施放鋒芒貫穿的方向來躲避技能。"],"tags":["Marksman"],"partype":"Mana","info":{"attack":8,"defense":5,"magic":3,"difficulty":8},"stats":{"hp":420.0,"hpperlevel":80.0,"mp":230.0,"mpperlevel":41.0,"movespeed":335.0,"armor":19.0,"armorperlevel":3.0,"spellblock":30.0,"spellblockperlevel":0.0,"attackrange":500.0,"hpregen":5.1,"hpregenperlevel":0.65,"mpregen":7.0,"mpregenperlevel":0.7,"crit":0.0,"critperlevel":0.0,"attackdamage":49.0,"attackdamageperlevel":3.0,"attackspeedoffset":-0.02,"attackspeedperlevel":3.3},"spells":[{"id":"LucianQ","name":"鋒芒貫穿","description":"路西恩向目標射出一道銳利的光束。","tooltip":"路西恩朝敵方單位射擊一道銳利的光束，對在光束直線範圍中的敵人造成 {{ e1 }} <span class=\"colorFF8C00\">（+{{ f1 }}）</span> （{{ e2 }}% 額外物理攻擊）物理傷害。","leveltip":{"label":["傷害","額外物理傷害","冷卻時間","消耗魔力"],"effect":["{{ e1 }} -> {{ e1NL }}","{{ e2 }}% -> {{ e2NL }}%","{{ cooldown }} -> {{ cooldownnNL }}","{{ cost }} -> {{ costnNL }}"]},"maxrank":5,"cooldown":[9,8,7,6,5],"cooldownBurn":"9/8/7/6/5","cost":[50,55,60,65,70],"costBurn":"50/55/60/65/70","effect":[null,[80,110,140,170,200],[60,75,90,105,120]],"effectBurn":[null,"80/110/140/170/200","60/75/90/105/120"],"vars":[{"link":"attackdamage","coeff":[0.6,0.75,0.9,1.05,1.2],"key":"f1"}],"costType":"Mana","range":[500,500,500,500,500],"rangeBurn":"500","image":{"full":"LucianQ.png","sprite":"spell5.png","group":"spell","x":432,"y":0,"w":48,"h":48},"resource":"{{ cost }} 魔力"},{"id":"LucianW","name":"烈炎鐵血","description":"路西恩發射一枚導彈，爆炸時會迸發星形火花並且標記敵人。被標記的敵人將會受到額外的傷害，路西恩擊中被標記的敵人會獲得額外跑速。","tooltip":"朝敵方單位射擊，並且在接觸到敵人時或是在技能路徑結束處爆炸，造成 {{ e1 }} <span class=\"color88FF88\">（+{{ a1 }}）</span> <span class=\"colorFF8C00\">（+{{ f1 }}）</span>魔法傷害並且標記敵人 6 秒。<br><br>攻擊被標記的目標將會提高路西恩 {{ e2 }} 跑速，持續 2 秒。","leveltip":{"label":["傷害","冷卻時間</br>"],"effect":["{{ e1 }} -> {{ e1NL }}","{{ cooldown }} -> {{ cooldownnNL }}"]},"maxrank":5,"cooldown":[14,13,12,11,10],"cooldownBurn":"14/13/12/11/10","cost":[60,60,60,60,60],"costBurn":"60","effect":[null,[60,100,140,180,220],[40,40,40,40,40],[10,14,18,22,26]],"effectBurn":[null,"60/100/140/180/220","40","10/14/18/22/26"],"vars":[{"link":"spelldamage","coeff":0.9,"key":"a1"},{"link":"bonusattackdamage","coeff":0.6,"key":"f1"}],"costType":"Mana","range":[1000,1000,1000,1000,1000],"rangeBurn":"1000","image":{"full":"LucianW.png","sprite":"spell5.png","group":"spell","x":0,"y":48,"w":48,"h":48},"resource":"{{ cost }} 魔力"},{"id":"LucianE","name":"冷酷進擊","description":"路西恩向前衝刺一小段距離，並移除所有緩速效果。光之獵手的攻擊將減少冷酷進擊的冷卻時間。","tooltip":"路西恩向前衝刺一小段距離，並移除所有緩速效果。<br><br>不論何時光之獵手命中敵方單位，冷酷進擊的冷卻時間將會減少 {{ e1 }} 秒（命中敵方英雄則加倍，提高到 {{ e2 }} 秒）。","leveltip":{"label":["冷卻時間"],"effect":["{{ cooldown }} -> {{ cooldownnNL }}"]},"maxrank":5,"cooldown":[14,13,12,11,10],"cooldownBurn":"14/13/12/11/10","cost":[0,0,0,0,0],"costBurn":"0","effect":[null,[1,1,1,1,1],[2,2,2,2,2]],"effectBurn":[null,"1","2"],"vars":[],"costType":"NoCost","range":[445,445,445,445,445],"rangeBurn":"445","image":{"full":"LucianE.png","sprite":"spell5.png","group":"spell","x":48,"y":48,"w":48,"h":48},"resource":"無消耗"},{"id":"LucianR","name":"赤色屠戮","description":"路西恩從他的武器中釋放連續射擊。","tooltip":"路西恩僅限朝向單一方向開火時，可以迅速自由地移動，持續 {{ e1 }} 秒。 他的每發射擊在接觸到第一個敵人之後爆裂造成 {{ e2 }} <span class=\"color88FF88\">（+{{ a1 }}）</span> <span class=\"colorFF8C00\">（+{{ a2 }}）</span> 物理傷害。 可射擊的次數隨著路西恩的攻速調整。 <span class=\"colorFF0000\">{{ f2 }} </span>次射擊可以造成的傷害總量：  {{ f1 }} 物理傷害。赤色屠戮對士兵造成 400% 的傷害。<br><br>路西恩在使用赤色屠戮的當下可以同時施放冷酷進擊。<br><br>重新啟動赤色屠戮可以提早取消技能。","leveltip":{"label":["傷害","冷卻時間"],"effect":["{{ e2 }} -> {{ e2NL }}","{{ cooldown }} -> {{ cooldownnNL }}"]},"maxrank":3,"cooldown":[100,75,50],"cooldownBurn":"100/75/50","cost":[100,100,100],"costBurn":"100","effect":[null,[3,3,3],[40,50,60],[2.5,3,3.5],[2.5,2.5,2.5]],"effectBurn":[null,"3","40/50/60","2.5/3/3.5","2.5"],"vars":[{"link":"spelldamage","coeff":0.1,"key":"a1"},{"link":"bonusattackdamage","coeff":0.25,"key":"a2"}],"costType":"Mana","range":[1400,1400,1400],"rangeBurn":"1400","image":{"full":"LucianR.png","sprite":"spell5.png","group":"spell","x":96,"y":48,"w":48,"h":48},"resource":"{{ cost }} 魔力"}],"passive":{"name":"光之獵手","description":"不論何處，路西恩只要使用技能，路西恩的下次普攻將可以發射兩次。","image":{"full":"Lucian_Passive.png","sprite":"passive1.png","group":"passive","x":384,"y":48,"w":48,"h":48}},"recommended":[{"champion":"Lucian","title":"LucianARAM","type":"riot","map":"12","mode":"ARAM","priority":false,"blocks":[{"type":"starting","items":[{"id":"1001","count":1},{"id":"1055","count":2},{"id":"2003","count":2}]},{"type":"essential","items":[{"id":"3006","count":1},{"id":"3181","count":1},{"id":"3046","count":1}]},{"type":"offensive","items":[{"id":"3071","count":1},{"id":"3031","count":1},{"id":"3184","count":1},{"id":"3035","count":1}]},{"type":"defensive","items":[{"id":"3102","count":1},{"id":"3139","count":1}]},{"type":"consumables","items":[]}]},{"champion":"Lucian","title":"LucianDM","type":"riot","map":"8","mode":"ODIN","priority":false,"blocks":[{"type":"starting","items":[{"id":"1001","count":1},{"id":"2003","count":2},{"id":"1062","count":1}]},{"type":"essential","items":[{"id":"3006","count":1},{"id":"3134","count":1},{"id":"3181","count":1}]},{"type":"offensive","items":[{"id":"3071","count":1},{"id":"3078","count":1},{"id":"3035","count":1}]},{"type":"defensive","items":[{"id":"3137","count":1},{"id":"3172","count":1},{"id":"3180","count":1}]},{"type":"consumables","items":[{"id":"2044","count":1},{"id":"2003","count":1},{"id":"2004","count":1}]}]},{"champion":"Lucian","title":"LucianFB","type":"riot","map":"12","mode":"FIRSTBLOOD","priority":false,"blocks":[{"type":"starting","items":[{"id":"1075","count":1},{"id":"2003","count":1},{"id":"3342","count":1}]},{"type":"essential","items":[{"id":"3006","count":1},{"id":"3181","count":1},{"id":"3078","count":1}]},{"type":"offensive","items":[{"id":"3035","count":1},{"id":"3031","count":1},{"id":"3153","count":1},{"id":"3071","count":1}]},{"type":"defensive","items":[{"id":"3026","count":1},{"id":"3172","count":1},{"id":"3102","count":1}]},{"type":"consumables","items":[{"id":"2003","count":1},{"id":"2004","count":1},{"id":"2037","count":1},{"id":"2043","count":1},{"id":"2044","count":1}]}]},{"champion":"Lucian","title":"LucianTT","type":"riot","map":"10","mode":"CLASSIC","priority":false,"blocks":[{"type":"starting","items":[{"id":"1001","count":1},{"id":"1055","count":1}]},{"type":"essential","items":[{"id":"3006","count":1},{"id":"3181","count":1},{"id":"3078","count":1}]},{"type":"offensive","items":[{"id":"3071","count":1},{"id":"3035","count":1},{"id":"3122","count":1},{"id":"3104","count":1}]},{"type":"defensive","items":[{"id":"3102","count":1},{"id":"3137","count":1},{"id":"3172","count":1},{"id":"2041","count":1}]},{"type":"consumables","items":[{"id":"2003","count":1},{"id":"2004","count":1},{"id":"2040","count":1}]}]}]}}}